ovos_vad_plugin_energy/__init__.py
ovos_vad_plugin_energy/energy.py
ovos_vad_plugin_energy/version.py
ovos_vad_plugin_energy-0.0.0.dist-info/LICENSE
ovos_vad_plugin_energy-0.0.0.dist-info/METADATA
ovos_vad_plugin_energy-0.0.0.dist-info/WHEEL
ovos_vad_plugin_energy-0.0.0.dist-info/entry_points.txt
ovos_vad_plugin_energy-0.0.0.dist-info/top_level.txt
ovos_vad_plugin_energy-0.0.0.dist-info/zip-safe
ovos_vad_plugin_energy-0.0.0.dist-info/RECORD
